mcp_server_metatool/__init__.py
mcp_server_metatool/__main__.py
mcp_server_metatool/server.py
mcp_server_metatool-0.0.4.dist-info/LICENSE
mcp_server_metatool-0.0.4.dist-info/METADATA
mcp_server_metatool-0.0.4.dist-info/WHEEL
mcp_server_metatool-0.0.4.dist-info/entry_points.txt
mcp_server_metatool-0.0.4.dist-info/top_level.txt
mcp_server_metatool-0.0.4.dist-info/RECORD
