Metadata-Version: 2.2
Name: mcp-server-metatool
Version: 0.0.4
Summary: Metatool MCP Server
Author: James Zhang
Author-email: James Zhang <james@jczstudio.com>
License:                                  Apache License
Project-URL: homepage, https://github.com/metatool-ai/mcp-server-metatool
Project-URL: repository, https://github.com/metatool-ai/mcp-server-metatool
Classifier: Programming Language :: Python :: 3.10
Requires-Python: >=3.10
License-File: LICENSE
Requires-Dist: mcp
Dynamic: author
Dynamic: requires-python
